setup.py
package_AWSO/__init__.py
package_AWSO/module_AWSO.py
package_AWSO.egg-info/PKG-INFO
package_AWSO.egg-info/SOURCES.txt
package_AWSO.egg-info/dependency_links.txt
package_AWSO.egg-info/not-zip-safe
package_AWSO.egg-info/top_level.txt