Metadata-Version: 2.1
Name: package-AWSO
Version: 0.1
Summary: Transaction and operation over AdventureWorksSalesOrders
Author-email: hernangarciamayoral@gmail.com
License: UNKNOWN
Platform: UNKNOWN
